composer_trade_mcp/__init__.py
composer_trade_mcp/__main__.py
composer_trade_mcp/server.py
composer_trade_mcp/schemas/__init__.py
composer_trade_mcp/schemas/api.py
composer_trade_mcp/schemas/asset_classes_schema.py
composer_trade_mcp/schemas/backtest_api.py
composer_trade_mcp/schemas/symphony_score_schema.py
composer_trade_mcp/utils/__init__.py
composer_trade_mcp/utils/auth.py
composer_trade_mcp/utils/parsers.py
composer_trade_mcp-0.1.7.dist-info/METADATA
composer_trade_mcp-0.1.7.dist-info/WHEEL
composer_trade_mcp-0.1.7.dist-info/entry_points.txt
composer_trade_mcp-0.1.7.dist-info/licenses/LICENSE
composer_trade_mcp-0.1.7.dist-info/RECORD
