Metadata-Version: 2.4
Name: composer-trade-mcp
Version: 0.1.7
Summary: Composer MCP Server - Backtest and Automate your trades with LLMs
Project-URL: Homepage, https://github.com/invest-composer/composer-trade-mcp
Project-URL: Repository, https://github.com/invest-composer/composer-trade-mcp.git
Project-URL: Documentation, https://github.com/invest-composer/composer-trade-mcp#readme
Project-URL: Issues, https://github.com/invest-composer/composer-trade-mcp/issues
Author-email: "Composer Technologies Inc." <help@composer.trade>
License-Expression: MIT
License-File: LICENSE
Keywords: ai-crypto-trader,ai-stock-trader,ai-trading,algorithmic-trading,automated-trading,backtesting,composer,financial-technology,fintech,investment-automation,llm,mcp,no-code-trading,portfolio-management,quantitative-trading,risk-management,symphony-trading,trading-execution,trading-strategies
Classifier: Development Status :: 4 - Beta
Classifier: Intended Audience :: Developers
Classifier: License :: OSI Approved :: MIT License
Classifier: Programming Language :: Python :: 3
Classifier: Programming Language :: Python :: 3.10
Classifier: Programming Language :: Python :: 3.11
Classifier: Programming Language :: Python :: 3.12
Classifier: Topic :: Software Development :: Libraries :: Python Modules
Requires-Python: >=3.10
Requires-Dist: asyncio>=3.4.3
Requires-Dist: fastmcp>=2.8.1
Requires-Dist: httpx>=0.28.1
Requires-Dist: pydantic>=2.11.7
